gitlab2pandas/__init__.py
gitlab2pandas/core.py
gitlab2pandas/extractions.py
gitlab2pandas/gitlab2pandas.py
gitlab2pandas/processing.py
gitlab2pandas-0.0.5.dist-info/LICENSE
gitlab2pandas-0.0.5.dist-info/METADATA
gitlab2pandas-0.0.5.dist-info/WHEEL
gitlab2pandas-0.0.5.dist-info/top_level.txt
gitlab2pandas-0.0.5.dist-info/RECORD
