Metadata-Version: 2.1
Name: gitlab2pandas
Version: 0.0.5
Summary: gitlab2pandas supports the aggregation of project activities in a GitLab repository and makes them available in pandas dataframes.
Home-page: https://gitlab.com/gitlab-learning-analytics/gitlab2pandas
Download-URL: https://gitlab.com/gitlab-learning-analytics/gitlab2pandas/-/archive/main/gitlab2pandas-main.zip
Author: Maximilian Karl
License: BSD 2
Keywords: git,gitlab,collaborative code development,git mining
Classifier: Programming Language :: Python :: 3
Classifier: Operating System :: OS Independent
Requires-Python: >=3.9
License-File: LICENSE
Requires-Dist: human-id (>=0.2.0)
Requires-Dist: pandas (>=1.4.4)
Requires-Dist: python-gitlab (>=3.9.0)
Requires-Dist: XlsxWriter (>=3.0.3)
